Workbook

Sheet Budget
A2: TIMBERLINE BUILD CO.
A4: PROJECT BUDGET — INTERNAL WORKING DOCUMENT
A5: Client Name: | B5: Hank Fos | E5: Date: | F5: 46147
A6: Project Address: | B6: 7 St Elizabeth, Laguna Niguel, CA 92677 | E6: Default Markup: | F6: 0.4
A7: Project Type: | B7: Master Bathroom Remodel | E7: Project #:
A8: Estimator: | B8: Justin | E8: License #:
A10: Category | B10: Item / Description | C10: Material Cost | D10: Labor Cost | E10: M&L Total | F10: Markup % | G10: Client Price | H10: Mat. Allowance? | I10: Notes
C11: what YOU pay | D11: what YOU pay | E11: =C+D | F11: default 40% | G11: =E×(1+F) | H11: ✔ = excl. Gary
A12: ▸ DEMO
B13: Demo & Haul Away | E13: =IFERROR(C13+D13,0) | F13: =$F$6 | G13: =IFERROR(E13*(1+F13),0) | H13: —
B14: Dumpster Rental | E14: =IFERROR(C14+D14,0) | F14: =$F$6 | G14: =IFERROR(E14*(1+F14),0) | H14: —
A15: Demo Subtotal | C15: =SUM(C13:C14) | D15: =SUM(D13:D14) | E15: =SUM(E13:E14) | G15: =SUM(G13:G14) | H15: =SUMIF(H13:H14,"✔",G13:G14)
A17: ▸ KITCHEN
B18: Cabinet Install | E18: =IFERROR(C18+D18,0) | F18: =$F$6 | G18: =IFERROR(E18*(1+F18),0) | H18: —
B19: Cabinets (Material Allowance) | E19: =IFERROR(C19+D19,0) | F19: =$F$6 | G19: =IFERROR(E19*(1+F19),0) | H19: ✔
B20: Countertop Install | E20: =IFERROR(C20+D20,0) | F20: =$F$6 | G20: =IFERROR(E20*(1+F20),0) | H20: —
B21: Countertop Material | E21: =IFERROR(C21+D21,0) | F21: =$F$6 | G21: =IFERROR(E21*(1+F21),0) | H21: ✔
B22: Backsplash — Labor | E22: =IFERROR(C22+D22,0) | F22: =$F$6 | G22: =IFERROR(E22*(1+F22),0) | H22: —
B23: Backsplash — Material | E23: =IFERROR(C23+D23,0) | F23: =$F$6 | G23: =IFERROR(E23*(1+F23),0) | H23: ✔
B24: Plumbing (rough + finish) | E24: =IFERROR(C24+D24,0) | F24: =$F$6 | G24: =IFERROR(E24*(1+F24),0) | H24: —
B25: Electrical | E25: =IFERROR(C25+D25,0) | F25: =$F$6 | G25: =IFERROR(E25*(1+F25),0) | H25: —
B26: Fixtures Allowance | E26: =IFERROR(C26+D26,0) | F26: =$F$6 | G26: =IFERROR(E26*(1+F26),0) | H26: ✔
B27: Appliance Hookup | E27: =IFERROR(C27+D27,0) | F27: =$F$6 | G27: =IFERROR(E27*(1+F27),0) | H27: —
B28: Drywall Repair | E28: =IFERROR(C28+D28,0) | F28: =$F$6 | G28: =IFERROR(E28*(1+F28),0) | H28: —
B29: Paint | E29: =IFERROR(C29+D29,0) | F29: =$F$6 | G29: =IFERROR(E29*(1+F29),0) | H29: —
A30: Kitchen Subtotal | C30: =SUM(C18:C29) | D30: =SUM(D18:D29) | E30: =SUM(E18:E29) | G30: =SUM(G18:G29) | H30: =SUMIF(H18:H29,"✔",G18:G29)
A32: ▸ BATHROOM
B33: Demo & Haul Away | C33: 0 | D33: 1000 | E33: =IFERROR(C33+D33,0) | F33: =$F$6 | G33: =IFERROR(E33*(1+F33),0) | H33: —
B34: Waterproofing / Hot Mop | C34: 0 | D34: 550 | E34: =IFERROR(C34+D34,0) | F34: =$F$6 | G34: =IFERROR(E34*(1+F34),0) | H34: —
B35: Tile Labor — Shower & Toilet Room Walls (96" high, niche) | C35: 0 | D35: 3400 | E35: =IFERROR(C35+D35,0) | F35: =$F$6 | G35: =IFERROR(E35*(1+F35),0) | H35: —
B36: Shower Tile (Allowance) | C36: 1600 | D36: 0 | E36: =IFERROR(C36+D36,0) | F36: 0 | G36: =IFERROR(E36*(1+F36),0) | H36: ✔
B37: Plumbing — Shower, 2 Sinks, Bidet Rough-in | C37: 0 | D37: 1000 | E37: =IFERROR(C37+D37,0) | F37: =$F$6 | G37: =IFERROR(E37*(1+F37),0) | H37: —
B38: Floor Tile (Allowance) | C38: 500 | D38: 0 | E38: =IFERROR(C38+D38,0) | F38: 0 | G38: =IFERROR(E38*(1+F38),0) | H38: ✔
B39: Set Vanity + Plumb 2 Sinks (client-supplied vanity/faucets) | C39: 0 | D39: 600 | E39: =IFERROR(C39+D39,0) | F39: =$F$6 | G39: =IFERROR(E39*(1+F39),0) | H39: —
B40: Double Sink Vanity (Allowance) | C40: 1000 | D40: 0 | E40: =IFERROR(C40+D40,0) | F40: 0 | G40: =IFERROR(E40*(1+F40),0) | H40: ✔
B41: Bidet Toilet (Allowance — Pass-through) | C41: 1000 | D41: 0 | E41: =IFERROR(C41+D41,0) | F41: 0 | G41: =IFERROR(E41*(1+F41),0) | H41: ✔
B42: Pocket Door — Frame + Install | C42: 0 | D42: 1200 | E42: =IFERROR(C42+D42,0) | F42: =$F$6 | G42: =IFERROR(E42*(1+F42),0) | H42: —
B43: Electrical — Bidet Circuit, Vent Fan, Mirror Lights x2, Relocate Switch/Outlet | C43: 0 | D43: 900 | E43: =IFERROR(C43+D43,0) | F43: =$F$6 | G43: =IFERROR(E43*(1+F43),0) | H43: —
B44: Drywall / Backer / Soffit Removal + Patch | C44: 0 | D44: 800 | E44: =IFERROR(C44+D44,0) | F44: =$F$6 | G44: =IFERROR(E44*(1+F44),0) | H44: —
B45: Hang Mirrors (owner-supplied), Towel Bar, TP Holder | C45: 0 | D45: 150 | E45: =IFERROR(C45+D45,0) | F45: =$F$6 | G45: =IFERROR(E45*(1+F45),0) | H45: —
B46: Sliding Closet Doors + Track (Allowance) | C46: 700 | D46: 0 | E46: =IFERROR(C46+D46,0) | F46: 0 | G46: =IFERROR(E46*(1+F46),0) | H46: ✔
B47: Sliding Closet Door Install Labor + Floor Protection | C47: 0 | D47: 550 | E47: =IFERROR(C47+D47,0) | F47: =$F$6 | G47: =IFERROR(E47*(1+F47),0) | H47: —
A48: Bathroom Subtotal | C48: =SUM(C33:C47) | D48: =SUM(D33:D47) | E48: =SUM(E33:E47) | G48: =SUM(G33:G47) | H48: =SUMIF(H33:H47,"✔",G33:G47)
A50: ▸ FLOORING
B51: Floor Demo | E51: =IFERROR(C51+D51,0) | F51: =$F$6 | G51: =IFERROR(E51*(1+F51),0) | H51: —
B52: Flooring — Install | E52: =IFERROR(C52+D52,0) | F52: =$F$6 | G52: =IFERROR(E52*(1+F52),0) | H52: —
B53: Flooring — Material | E53: =IFERROR(C53+D53,0) | F53: =$F$6 | G53: =IFERROR(E53*(1+F53),0) | H53: ✔
B54: Baseboard | E54: =IFERROR(C54+D54,0) | F54: =$F$6 | G54: =IFERROR(E54*(1+F54),0) | H54: —
A55: Flooring Subtotal | C55: =SUM(C51:C54) | D55: =SUM(D51:D54) | E55: =SUM(E51:E54) | G55: =SUM(G51:G54) | H55: =SUMIF(H51:H54,"✔",G51:G54)
A57: ▸ PAINT & DRYWALL
B58: Interior Paint | E58: =IFERROR(C58+D58,0) | F58: =$F$6 | G58: =IFERROR(E58*(1+F58),0) | H58: —
B59: Drywall Repair / Texture | E59: =IFERROR(C59+D59,0) | F59: =$F$6 | G59: =IFERROR(E59*(1+F59),0) | H59: —
B60: Popcorn Ceiling Removal | E60: =IFERROR(C60+D60,0) | F60: =$F$6 | G60: =IFERROR(E60*(1+F60),0) | H60: —
B61: Exterior Paint | E61: =IFERROR(C61+D61,0) | F61: =$F$6 | G61: =IFERROR(E61*(1+F61),0) | H61: —
A62: Paint & Drywall Subtotal | C62: =SUM(C58:C61) | D62: =SUM(D58:D61) | E62: =SUM(E58:E61) | G62: =SUM(G58:G61) | H62: =SUMIF(H58:H61,"✔",G58:G61)
A64: ▸ ELECTRICAL
B65: Panel / Subpanel Work | E65: =IFERROR(C65+D65,0) | F65: =$F$6 | G65: =IFERROR(E65*(1+F65),0) | H65: —
B66: Recessed Lights | E66: =IFERROR(C66+D66,0) | F66: =$F$6 | G66: =IFERROR(E66*(1+F66),0) | H66: —
B67: Outlets / Switches | E67: =IFERROR(C67+D67,0) | F67: =$F$6 | G67: =IFERROR(E67*(1+F67),0) | H67: —
B68: Ceiling Fans | E68: =IFERROR(C68+D68,0) | F68: =$F$6 | G68: =IFERROR(E68*(1+F68),0) | H68: —
A69: Electrical Subtotal | C69: =SUM(C65:C68) | D69: =SUM(D65:D68) | E69: =SUM(E65:E68) | G69: =SUM(G65:G68) | H69: =SUMIF(H65:H68,"✔",G65:G68)
A71: ▸ PLUMBING
B72: Rough Plumbing | E72: =IFERROR(C72+D72,0) | F72: =$F$6 | G72: =IFERROR(E72*(1+F72),0) | H72: —
B73: Finish Plumbing | E73: =IFERROR(C73+D73,0) | F73: =$F$6 | G73: =IFERROR(E73*(1+F73),0) | H73: —
B74: Water Heater | E74: =IFERROR(C74+D74,0) | F74: =$F$6 | G74: =IFERROR(E74*(1+F74),0) | H74: —
B75: Gas Line | E75: =IFERROR(C75+D75,0) | F75: =$F$6 | G75: =IFERROR(E75*(1+F75),0) | H75: —
A76: Plumbing Subtotal | C76: =SUM(C72:C75) | D76: =SUM(D72:D75) | E76: =SUM(E72:E75) | G76: =SUM(G72:G75) | H76: =SUMIF(H72:H75,"✔",G72:G75)
A78: ▸ MISC / EXTRA
B79: Shower Glass Enclosure (68x34, semi-frameless) | C79: 0 | D79: 1600 | E79: =IFERROR(C79+D79,0) | F79: =$F$6 | G79: =IFERROR(E79*(1+F79),0) | H79: — | I79: Upgrade to full frameless ~+$500
B80: Mirror Lights x2 (Allowance) | C80: 500 | D80: 0 | E80: =IFERROR(C80+D80,0) | F80: 0 | G80: =IFERROR(E80*(1+F80),0) | H80: ✔
B81: Hauling / Dumpster | E81: =IFERROR(C81+D81,0) | F81: =$F$6 | G81: =IFERROR(E81*(1+F81),0) | H81: —
B82: Optional Item | E82: =IFERROR(C82+D82,0) | F82: =$F$6 | G82: =IFERROR(E82*(1+F82),0) | H82: —
B83: Optional Item 2 | E83: =IFERROR(C83+D83,0) | F83: =$F$6 | G83: =IFERROR(E83*(1+F83),0) | H83: —
A84: Misc / Extra Subtotal | C84: =SUM(C79:C83) | D84: =SUM(D79:D83) | E84: =SUM(E79:E83) | G84: =SUM(G79:G83) | H84: =SUMIF(H79:H83,"✔",G79:G83)
A87: PROJECT TOTALS
A88: Your Total Cost (Materials + Labor) | C88: =SUM(C15,C30,C48,C55,C62,C69,C76,C84) | D88: =SUM(D15,D30,D48,D55,D62,D69,D76,D84) | E88: =SUM(E15,E30,E48,E55,E62,E69,E76,E84) | G88: =SUM(E15,E30,E48,E55,E62,E69,E76,E84)
A89: Total Material Allowances (excl. from Gary's cut) | G89: =SUM(H15,H30,H48,H55,H62,H69,H76,H84)
A90: CLIENT TOTAL (with markup) | G90: =SUM(G15,G30,G48,G55,G62,G69,G76,G84)
A91: Gary's Cut (10% × (Client Total − Material Allowances)) | G91: =(G90-G89)*0.10
A92: Gross Profit (Client Total − Your Cost) | G92: =G90-G88
A93: MY TAKE HOME (Profit − Gary's Cut) | G93: =G92-G91
A95: CHANGE ORDERS
A96: Description | E96: Cost | F96: Markup % | G96: Client Charge | H96: Approved? | I96: Date
F97: =$F$6 | G97: =IFERROR(E97*(1+F97),0)
F98: =$F$6 | G98: =IFERROR(E98*(1+F98),0)
F99: =$F$6 | G99: =IFERROR(E99*(1+F99),0)
F100: =$F$6 | G100: =IFERROR(E100*(1+F100),0)
F101: =$F$6 | G101: =IFERROR(E101*(1+F101),0)
F102: =$F$6 | G102: =IFERROR(E102*(1+F102),0)
A103: Change Order Total | G103: =SUM(G97:G102)

Sheet Materials
A2: TIMBERLINE BUILD CO.
A4: MATERIALS TRACKER
A5: Item / Description | B5: Supplier | C5: Unit Cost | D5: Qty | E5: Total | F5: Status | G5: Notes
E6: =IFERROR(C6*D6,"")
E7: =IFERROR(C7*D7,"")
E8: =IFERROR(C8*D8,"")
E9: =IFERROR(C9*D9,"")
E10: =IFERROR(C10*D10,"")
E11: =IFERROR(C11*D11,"")
E12: =IFERROR(C12*D12,"")
E13: =IFERROR(C13*D13,"")
E14: =IFERROR(C14*D14,"")
E15: =IFERROR(C15*D15,"")
E16: =IFERROR(C16*D16,"")
E17: =IFERROR(C17*D17,"")
... E50: =IFERROR(C50*D50,"")
A51: Total Materials Cost | E51: =SUM(E6:E50)

Sheet Client Summary
A2: TIMBERLINE BUILD CO.
A4: INVESTMENT ESTIMATE
A6: Client: | B6: =Budget!B5
A7: Property: | B7: =Budget!B6
A8: Project Type: | B8: =Budget!B7
A9: Estimate Date: | B9: =Budget!F5
A11: SCOPE OF WORK — COST BREAKDOWN
A12: Demo | B12: =Budget!G15
A13: Kitchen | B13: =Budget!G30
A14: Bathroom | B14: =Budget!G48
A15: Flooring | B15: =Budget!G55
A16: Paint & Drywall | B16: =Budget!G62
A17: Electrical | B17: =Budget!G69
A18: Plumbing | B18: =Budget!G76
A19: Misc / Extra | B19: =Budget!G84
A21: TOTAL PROJECT INVESTMENT | B21: =Budget!G90
A23: timberlinebuild.co · Estimate valid 30 days · CA Contractor License #pending

Sheet Profit Breakdown
A2: TIMBERLINE BUILD CO.
A4: JOB PROFIT BREAKDOWN
A6: Client Name | B6: =Budget!B5
A7: Project Address | B7: =Budget!B6
A8: Project Type | B8: =Budget!B7
A9: Date | B9: =Budget!F5
A11: CLIENT TOTAL | B11: =Budget!G90
A12: Your Total Cost | B12: =Budget!G88
A13: Material Allowances | B13: =Budget!G89
A14: Gross Profit | B14: =Budget!G92
A15: Gary's Cut (10%) | B15: =Budget!G91
A16: Change Orders | B16: =Budget!G103
A17: MY TAKE HOME | B17: =Budget!G93+Budget!G103
A19: Profit Margin % | B19: =IFERROR(B17/B11,0)
A20: Effective Markup % | B20: =IFERROR((B11-B12)/B12,0)
A22: PAYMENT TRACKING
A23: Payment # | B23: Amount | C23: Date
A24: Payment 1
A25: Payment 2
A26: Payment 3
A27: Payment 4
A28: Payment 5
A29: Payment 6
A30: Total Paid | B30: =SUM(B24:B29) | C30: =B11-B30
